{
  "A6020": [
    {
      "changelog": "- Blacklisted google hotword service to fix mic issues\r\n- Enabled audiosphere effect by default\r\n- Fixed FM radio\r\n- Fixed postprocessing daemon crashes\r\n- Misc changes for infra", 
      "maintainer": "Adithya R", 
      "model": "Vibe K5", 
      "oem": "Lenovo", 
      "v10.0": [
        {
          "OFFICIAL": [
            {
              "GAPPS": [
                {
                  "date": "2020-12-28", 
                  "datetime": "20201228", 
                  "filename": "Arrow-v10.0-A6020-OFFICIAL-20201228-GAPPS.zip", 
                  "filepath": "/arrow-10.0/A6020/Arrow-v10.0-A6020-OFFICIAL-20201228-GAPPS.zip", 
                  "sha256": "0067d9d73a467f5bc81eb33d886b4d5548474eac52c380e6fd6cb6e1eaf8a495", 
                  "size": "735572547", 
                  "type": "official", 
                  "version": "v10.0"
                }
              ], 
              "VANILLA": [
                {
                  "date": "2020-12-28", 
                  "datetime": "20201228", 
                  "filename": "Arrow-v10.0-A6020-OFFICIAL-20201228-VANILLA.zip", 
                  "filepath": "/arrow-10.0/A6020/Arrow-v10.0-A6020-OFFICIAL-20201228-VANILLA.zip", 
                  "sha256": "722e8ea33aafe3beff281775a0fdd2ead841c0d70d02c714fa2a6b0834a15e55", 
                  "size": "576493590", 
                  "type": "official", 
                  "version": "v10.0"
                }
              ]
            }
          ]
        }
      ]
    }
  ], 
  "X00T": [
    {
      "changelog": null, 
      "maintainer": "PranavKpr", 
      "model": "Asus Zenfone Max Pro M1", 
      "oem": "asus", 
      "v11.0": [
        {
          "OFFICIAL": [
            {
              "GAPPS": [
                {
                  "date": "2021-01-15", 
                  "datetime": "20210115", 
                  "filename": "Arrow-v11.0-X00T-OFFICIAL-20210115-GAPPS.zip", 
                  "filepath": "/arrow-11.0/X00T/Arrow-v11.0-X00T-OFFICIAL-20210115-GAPPS.zip", 
                  "sha256": "8a1a174354442e556c587c825c1c7e91618ec5060ccebec00ae4eb455f801b85", 
                  "size": "1068633571", 
                  "type": "official", 
                  "version": "v11.0"
                }
              ], 
              "VANILLA": [
                {
                  "date": "2021-01-15", 
                  "datetime": "20210115", 
                  "filename": "Arrow-v11.0-X00T-OFFICIAL-20210115-VANILLA.zip", 
                  "filepath": "/arrow-11.0/X00T/Arrow-v11.0-X00T-OFFICIAL-20210115-VANILLA.zip", 
                  "sha256": "581e4c98f2cc1cb6ee1ac82b1a2d748486dfd886d01ada60254671910265795b", 
                  "size": "752821314", 
                  "type": "official", 
                  "version": "v11.0"
                }
              ]
            }
          ], 
          "UNOFFICIAL": [
            {
              "GAPPS": [
                {
                  "date": "2021-01-14", 
                  "datetime": "20210114", 
                  "filename": "Arrow-v11.0-X00T-UNOFFICIAL-20210114-GAPPS.zip", 
                  "filepath": "/arrow-11.0/X00T/Arrow-v11.0-X00T-UNOFFICIAL-20210114-GAPPS.zip", 
                  "sha256": "20f102cf2f733005930ead3923026fd3ca073dca81dde119ab319f2f1a40918a", 
                  "size": "1066536655", 
                  "type": "unofficial", 
                  "version": "v11.0"
                }
              ], 
              "VANILLA": [
                {
                  "date": "2021-01-15", 
                  "datetime": "20210115", 
                  "filename": "Arrow-v11.0-X00T-UNOFFICIAL-20210115-VANILLA.zip", 
                  "filepath": "/arrow-11.0/X00T/Arrow-v11.0-X00T-UNOFFICIAL-20210115-VANILLA.zip", 
                  "sha256": "d1a748c52b68b0bcd1fada47fada6669efe43f9e3e0e217f88924841a8141737", 
                  "size": "752337019", 
                  "type": "unofficial", 
                  "version": "v11.0"
                }
              ]
            }
          ]
        }
      ]
    }
  ], 
  "beryllium": [
    {
      "changelog": "!!!WARNING!!!\r\nREQUEST ONLY CLEAN FLASH\r\n\r\n- Switch FBE and drop FDE (enable force encryption)\r\n- Update display, graphics, wfd and media blobs to R\r\n- Update display/audio/media hals to sdm710 R\r\n- Fixed WFD\r\n- Fixed \"Ok, Google\" with screen off\r\n- Switch to aidl Light HAL and update values\r\n- Fixed color display problems in some apps\r\n- Many fixes and upstream changes.\r\n\r\nNote:\r\n- Don`t flash on previous build dirty, will bootloop and drop data.", 
      "maintainer": "Ganesh Varma, kubersharma001, palaych", 
      "model": "POCOPHONE F1", 
      "oem": "POCO", 
      "v10.0": [
        {
          "OFFICIAL": [
            {
              "GAPPS": [
                {
                  "date": "2020-12-27", 
                  "datetime": "20201227", 
                  "filename": "Arrow-v10.0-beryllium-OFFICIAL-20201227-GAPPS.zip", 
                  "filepath": "/arrow-10.0/beryllium/Arrow-v10.0-beryllium-OFFICIAL-20201227-GAPPS.zip", 
                  "sha256": "879bfcb9e84c025e27838c84b1708924761e1f1d837de57dd2efa9bdce971dfc", 
                  "size": "941260433", 
                  "type": "official", 
                  "version": "v10.0"
                }
              ], 
              "VANILLA": [
                {
                  "date": "2020-12-27", 
                  "datetime": "20201227", 
                  "filename": "Arrow-v10.0-beryllium-OFFICIAL-20201227-VANILLA.zip", 
                  "filepath": "/arrow-10.0/beryllium/Arrow-v10.0-beryllium-OFFICIAL-20201227-VANILLA.zip", 
                  "sha256": "eea19b07866c5610f3c4adeee30e869d29a8ec3f1276e724c92a2ea29b932dfa", 
                  "size": "781869994", 
                  "type": "official", 
                  "version": "v10.0"
                }
              ]
            }
          ]
        }
      ], 
      "v11.0": [
        {
          "OFFICIAL": [
            {
              "GAPPS": [
                {
                  "date": "2021-01-14", 
                  "datetime": "20210114", 
                  "filename": "Arrow-v11.0-beryllium-OFFICIAL-20210114-GAPPS.zip", 
                  "filepath": "/arrow-11.0/beryllium/Arrow-v11.0-beryllium-OFFICIAL-20210114-GAPPS.zip", 
                  "sha256": "c9d5ac76ac4a368dccaec3dd093c44b3e3d42ccfb7a0e78fdf2da38778c16661", 
                  "size": "1195327933", 
                  "type": "official", 
                  "version": "v11.0"
                }
              ], 
              "VANILLA": [
                {
                  "date": "2021-01-14", 
                  "datetime": "20210114", 
                  "filename": "Arrow-v11.0-beryllium-OFFICIAL-20210114-VANILLA.zip", 
                  "filepath": "/arrow-11.0/beryllium/Arrow-v11.0-beryllium-OFFICIAL-20210114-VANILLA.zip", 
                  "sha256": "965ecd922b5ea7c9ca5d9e236ca8e506f486330cc4b90e36696c32e1cf1cc95d", 
                  "size": "879627949", 
                  "type": "official", 
                  "version": "v11.0"
                }
              ]
            }
          ], 
          "UNOFFICIAL": [
            {
              "GAPPS": [
                {
                  "date": "2020-12-12", 
                  "datetime": "20201212", 
                  "filename": "Arrow-v11.0-beryllium-UNOFFICIAL-20201212-GAPPS.zip", 
                  "filepath": "/arrow-11.0/beryllium/Arrow-v11.0-beryllium-UNOFFICIAL-20201212-GAPPS.zip", 
                  "sha256": "6e3d3d831f3a6b81edc617457b820b490e8a0a1da2c859b8176aa8c2535f8eb0", 
                  "size": "1177895909", 
                  "type": "unofficial", 
                  "version": "v11.0"
                }
              ], 
              "VANILLA": [
                {
                  "date": "2020-12-12", 
                  "datetime": "20201212", 
                  "filename": "Arrow-v11.0-beryllium-UNOFFICIAL-20201212-VANILLA.zip", 
                  "filepath": "/arrow-11.0/beryllium/Arrow-v11.0-beryllium-UNOFFICIAL-20201212-VANILLA.zip", 
                  "sha256": "6d56db5fbd1dc32636062f3f2a7e2ee7f4b1c068974e4eb0c3964a0dd5e863b7", 
                  "size": "858149777", 
                  "type": "unofficial", 
                  "version": "v11.0"
                }
              ]
            }
          ]
        }
      ]
    }
  ], 
  "cheeseburger": [
    {
      "changelog": null, 
      "maintainer": "Bauuuuu", 
      "model": "ONEPLUS A5000", 
      "oem": "OnePlus", 
      "v11.0": [
        {
          "OFFICIAL": [
            {
              "GAPPS": [
                {
                  "date": "2021-01-16", 
                  "datetime": "20210116", 
                  "filename": "Arrow-v11.0-cheeseburger-OFFICIAL-20210116-GAPPS.zip", 
                  "filepath": "/arrow-11.0/cheeseburger/Arrow-v11.0-cheeseburger-OFFICIAL-20210116-GAPPS.zip", 
                  "sha256": "f0d457ae17c9698443560a946895145b36bbb6a6475acf0ac4fed451d47db326", 
                  "size": "1191259126", 
                  "type": "official", 
                  "version": "v11.0"
                }
              ], 
              "VANILLA": [
                {
                  "date": "2021-01-16", 
                  "datetime": "20210116", 
                  "filename": "Arrow-v11.0-cheeseburger-OFFICIAL-20210116-VANILLA.zip", 
                  "filepath": "/arrow-11.0/cheeseburger/Arrow-v11.0-cheeseburger-OFFICIAL-20210116-VANILLA.zip", 
                  "sha256": "fa72af3bb0fe5a29c71428949f4f2349b682c54b60491daf0ce8887f2231bc49", 
                  "size": "871085813", 
                  "type": "official", 
                  "version": "v11.0"
                }
              ]
            }
          ], 
          "UNOFFICIAL": [
            {
              "GAPPS": [
                {
                  "date": "2021-01-14", 
                  "datetime": "20210114", 
                  "filename": "Arrow-v11.0-cheeseburger-UNOFFICIAL-20210114-GAPPS.zip", 
                  "filepath": "/arrow-11.0/cheeseburger/Arrow-v11.0-cheeseburger-UNOFFICIAL-20210114-GAPPS.zip", 
                  "sha256": "22903bd363baf20e93012cc7effbb9e428b4e069aa92ba2f1a403f1841eee34f", 
                  "size": "1190515868", 
                  "type": "unofficial", 
                  "version": "v11.0"
                }
              ], 
              "VANILLA": [
                {
                  "date": "2020-12-28", 
                  "datetime": "20201228", 
                  "filename": "Arrow-v11.0-cheeseburger-UNOFFICIAL-20201228-VANILLA.zip", 
                  "filepath": "/arrow-11.0/cheeseburger/Arrow-v11.0-cheeseburger-UNOFFICIAL-20201228-VANILLA.zip", 
                  "sha256": "1d07dd3eb33a5cd9c1dfb64a348137d7cb02e44b6ac18a209093c9d7a7bd7e45", 
                  "size": "866260454", 
                  "type": "unofficial", 
                  "version": "v11.0"
                }
              ]
            }
          ]
        }
      ]
    }
  ], 
  "chiron": [
    {
      "changelog": "- added Gcam from AOSP-11 for Sagit\r\n- undervolted CPU", 
      "maintainer": "WhiterWalt", 
      "model": "Mi MIX 2", 
      "oem": "Xiaomi", 
      "v11.0": [
        {
          "COMMUNITY": [
            {
              "GAPPS": [
                {
                  "date": "2021-01-15", 
                  "datetime": "20210115", 
                  "filename": "Arrow-v11.0-chiron-COMMUNITY-20210115-GAPPS.zip", 
                  "filepath": "/arrow-11.0/chiron/Arrow-v11.0-chiron-COMMUNITY-20210115-GAPPS.zip", 
                  "sha256": "76228e5ad69d029309c909504688c997b5a3c92ddbd638ab1b27fb9d274731af", 
                  "size": "1130147346", 
                  "type": "community", 
                  "version": "v11.0"
                }
              ], 
              "VANILLA": [
                {
                  "date": "2021-01-15", 
                  "datetime": "20210115", 
                  "filename": "Arrow-v11.0-chiron-COMMUNITY-20210115-VANILLA.zip", 
                  "filepath": "/arrow-11.0/chiron/Arrow-v11.0-chiron-COMMUNITY-20210115-VANILLA.zip", 
                  "sha256": "2797d52fb997e6054854f3b352d8d14829b87b848581b7543ea272d5cea6c72c", 
                  "size": "814709905", 
                  "type": "community", 
                  "version": "v11.0"
                }
              ]
            }
          ]
        }
      ]
    }
  ], 
  "clover": [
    {
      "changelog": "- Initial build.", 
      "maintainer": "TH779", 
      "model": "MI PAD 4", 
      "oem": "Xiaomi", 
      "v10.0": [
        {
          "OFFICIAL": [
            {
              "GAPPS": [
                {
                  "date": "2020-12-28", 
                  "datetime": "20201228", 
                  "filename": "Arrow-v10.0-clover-OFFICIAL-20201228-GAPPS.zip", 
                  "filepath": "/arrow-10.0/clover/Arrow-v10.0-clover-OFFICIAL-20201228-GAPPS.zip", 
                  "sha256": "40046a4edb49f7442c7ee549eee9ca0743933d182e2a574fed2dc36170196c53", 
                  "size": "850645125", 
                  "type": "official", 
                  "version": "v10.0"
                }
              ], 
              "VANILLA": [
                {
                  "date": "2020-12-28", 
                  "datetime": "20201228", 
                  "filename": "Arrow-v10.0-clover-OFFICIAL-20201228-VANILLA.zip", 
                  "filepath": "/arrow-10.0/clover/Arrow-v10.0-clover-OFFICIAL-20201228-VANILLA.zip", 
                  "sha256": "22aeba677628540a20bb9bfb77f4026f4c836c4b706b6b786e5baaf3744a2539", 
                  "size": "696968343", 
                  "type": "official", 
                  "version": "v10.0"
                }
              ]
            }
          ]
        }
      ], 
      "v11.0": [
        {
          "OFFICIAL": [
            {
              "GAPPS": [
                {
                  "date": "2021-01-04", 
                  "datetime": "20210104", 
                  "filename": "Arrow-v11.0-clover-OFFICIAL-20210104-GAPPS.zip", 
                  "filepath": "/arrow-11.0/clover/Arrow-v11.0-clover-OFFICIAL-20210104-GAPPS.zip", 
                  "sha256": "26a2558d81e17e4add335f3d989f6df06596fb1f338a6b8f9297c420fdd72ffd", 
                  "size": "1107844509", 
                  "type": "official", 
                  "version": "v11.0"
                }
              ], 
              "VANILLA": [
                {
                  "date": "2021-01-04", 
                  "datetime": "20210104", 
                  "filename": "Arrow-v11.0-clover-OFFICIAL-20210104-VANILLA.zip", 
                  "filepath": "/arrow-11.0/clover/Arrow-v11.0-clover-OFFICIAL-20210104-VANILLA.zip", 
                  "sha256": "702dee7da69c2e6e94108883b441a90fd6494cd75e5bf1cc0476b574096b428b", 
                  "size": "781811408", 
                  "type": "official", 
                  "version": "v11.0"
                }
              ]
            }
          ], 
          "UNOFFICIAL": [
            {
              "GAPPS": [
                {
                  "date": "2020-12-31", 
                  "datetime": "20201231", 
                  "filename": "Arrow-v11.0-clover-UNOFFICIAL-20201231-GAPPS.zip", 
                  "filepath": "/arrow-11.0/clover/Arrow-v11.0-clover-UNOFFICIAL-20201231-GAPPS.zip", 
                  "sha256": "b60084435e5b783b5c441a3891944320212a17af6fec5857f311b53183bf749c", 
                  "size": "1106157313", 
                  "type": "unofficial", 
                  "version": "v11.0"
                }
              ]
            }
          ]
        }
      ]
    }
  ], 
  "davinci": [
    {
      "changelog": "11/01/2021\r\n-Upstreamed the kernel to Linux 4.14.214\r\n-Minor cleanup\r\n07/01/2021\r\n-Improved performance and UX by switching to the Pixel Power HAL (libperfmgr)\r\n-Updated blobs from MIUI 20.12.28\r\n05/01/2021\r\n-Upstreamed the kernel to Linux 4.14.213\r\n30/12/2020\r\n-Improved FOD behaviour\r\n-Switched to AOSP Bluetooth\r\n-Updated blobs from MIUI 20.12.26\r\n\r\nNotes:\r\n- Recommended required firmware is MIUI 20.10.20 (China Beta)\r\n- Minimum firmware is MIUI V12.0.5.0\r\n- Recommended recovery is the OFFICIAL TWRP", 
      "maintainer": "daniml3", 
      "model": "Mi 9T", 
      "oem": "Xiaomi", 
      "v11.0": [
        {
          "OFFICIAL": [
            {
              "GAPPS": [
                {
                  "date": "2021-01-15", 
                  "datetime": "20210115", 
                  "filename": "Arrow-v11.0-davinci-OFFICIAL-20210115-GAPPS.zip", 
                  "filepath": "/arrow-11.0/davinci/Arrow-v11.0-davinci-OFFICIAL-20210115-GAPPS.zip", 
                  "sha256": "a592ec5bfdd44d9590d704152d988f06cae346cd0963884e350ca9d455d5e922", 
                  "size": "1323167247", 
                  "type": "official", 
                  "version": "v11.0"
                }
              ], 
              "VANILLA": [
                {
                  "date": "2021-01-15", 
                  "datetime": "20210115", 
                  "filename": "Arrow-v11.0-davinci-OFFICIAL-20210115-VANILLA.zip", 
                  "filepath": "/arrow-11.0/davinci/Arrow-v11.0-davinci-OFFICIAL-20210115-VANILLA.zip", 
                  "sha256": "3fd93f3148b6b84a7d31fadfbb04952e4bd343dde951a1ed2a5df050aac347c9", 
                  "size": "1004267915", 
                  "type": "official", 
                  "version": "v11.0"
                }
              ]
            }
          ], 
          "UNOFFICIAL": [
            {
              "GAPPS": [
                {
                  "date": "2020-12-11", 
                  "datetime": "20201211", 
                  "filename": "Arrow-v11.0-davinci-UNOFFICIAL-20201211-GAPPS.zip", 
                  "filepath": "/arrow-11.0/davinci/Arrow-v11.0-davinci-UNOFFICIAL-20201211-GAPPS.zip", 
                  "sha256": "4598336d1d25a186c1823c91dc8617da08cfc678166077e7173292a8c367c598", 
                  "size": "1189630406", 
                  "type": "unofficial", 
                  "version": "v11.0"
                }
              ], 
              "VANILLA": [
                {
                  "date": "2020-12-10", 
                  "datetime": "20201210", 
                  "filename": "Arrow-v11.0-davinci-UNOFFICIAL-20201210-VANILLA.zip", 
                  "filepath": "/arrow-11.0/davinci/Arrow-v11.0-davinci-UNOFFICIAL-20201210-VANILLA.zip", 
                  "sha256": "2bd3fedc383adde1efdc092e56f036bf776059420c1f43f7724e0f7f6db01a7d", 
                  "size": "978442577", 
                  "type": "unofficial", 
                  "version": "v11.0"
                }
              ]
            }
          ]
        }
      ]
    }
  ], 
  "dumpling": [
    {
      "changelog": "official release", 
      "maintainer": "TG_DEVICE_MAINTAINER", 
      "model": "ONEPLUS A5010", 
      "oem": "OnePlus", 
      "v11.0": [
        {
          "OFFICIAL": [
            {
              "GAPPS": [
                {
                  "date": "2021-01-15", 
                  "datetime": "20210115", 
                  "filename": "Arrow-v11.0-dumpling-OFFICIAL-20210115-GAPPS.zip", 
                  "filepath": "/arrow-11.0/dumpling/Arrow-v11.0-dumpling-OFFICIAL-20210115-GAPPS.zip", 
                  "sha256": "d79f67bfc7cc2733b157114f1c1f89c299a731fd8225ea2ebbcd581339b67dbd", 
                  "size": "1191417039", 
                  "type": "official", 
                  "version": "v11.0"
                }
              ], 
              "VANILLA": [
                {
                  "date": "2021-01-15", 
                  "datetime": "20210115", 
                  "filename": "Arrow-v11.0-dumpling-OFFICIAL-20210115-VANILLA.zip", 
                  "filepath": "/arrow-11.0/dumpling/Arrow-v11.0-dumpling-OFFICIAL-20210115-VANILLA.zip", 
                  "sha256": "dd1d4e5710e5fb1cb6e9858eef66467831da68e37b0725e1899ae9098e9575f7", 
                  "size": "871126376", 
                  "type": "official", 
                  "version": "v11.0"
                }
              ]
            }
          ]
        }
      ]
    }
  ], 
  "enchilada": [
    {
      "changelog": null, 
      "maintainer": "Raj Jadeja", 
      "model": "OnePlus6", 
      "oem": "OnePlus", 
      "v11.0": [
        {
          "OFFICIAL": [
            {
              "GAPPS": [
                {
                  "date": "2021-01-15", 
                  "datetime": "20210115", 
                  "filename": "Arrow-v11.0-enchilada-OFFICIAL-20210115-GAPPS.zip", 
                  "filepath": "/arrow-11.0/enchilada/Arrow-v11.0-enchilada-OFFICIAL-20210115-GAPPS.zip", 
                  "sha256": "6247ec56225a5019a83d50666422deaf4fe404f32d0b0fd1b0438509139a9ff8", 
                  "size": "959230103", 
                  "type": "official", 
                  "version": "v11.0"
                }
              ], 
              "VANILLA": [
                {
                  "date": "2021-01-15", 
                  "datetime": "20210115", 
                  "filename": "Arrow-v11.0-enchilada-OFFICIAL-20210115-VANILLA.zip", 
                  "filepath": "/arrow-11.0/enchilada/Arrow-v11.0-enchilada-OFFICIAL-20210115-VANILLA.zip", 
                  "sha256": "e959c26399549931e074f6f45b80a0ae1c9dc0c36f6bfde8ea2e1120d88823f4", 
                  "size": "675562144", 
                  "type": "official", 
                  "version": "v11.0"
                }
              ]
            }
          ], 
          "UNOFFICIAL": [
            {
              "VANILLA": [
                {
                  "date": "2020-12-07", 
                  "datetime": "20201207", 
                  "filename": "Arrow-v11.0-enchilada-UNOFFICIAL-20201207-VANILLA.zip", 
                  "filepath": "/arrow-11.0/enchilada/Arrow-v11.0-enchilada-UNOFFICIAL-20201207-VANILLA.zip", 
                  "sha256": "4db9b9c5deabf78a9bc1d6f05aaec6427ded90a649fcac291d1c9796ada48c15", 
                  "size": "663117117", 
                  "type": "unofficial", 
                  "version": "v11.0"
                }
              ]
            }
          ]
        }
      ]
    }
  ], 
  "ginkgo": [
    {
      "changelog": "- Upstreamed kernel to v4.14.213\r\n- Performance improvements", 
      "maintainer": "Adithya R", 
      "model": "Redmi Note 8", 
      "oem": "Xiaomi", 
      "v10.0": [
        {
          "OFFICIAL": [
            {
              "GAPPS": [
                {
                  "date": "2020-12-28", 
                  "datetime": "20201228", 
                  "filename": "Arrow-v10.0-ginkgo-OFFICIAL-20201228-GAPPS.zip", 
                  "filepath": "/arrow-10.0/ginkgo/Arrow-v10.0-ginkgo-OFFICIAL-20201228-GAPPS.zip", 
                  "sha256": "e251d71ef99f6553405fb9050187891e9da4b7a5406bb6409f2062d982e12fda", 
                  "size": "984807757", 
                  "type": "official", 
                  "version": "v10.0"
                }
              ], 
              "VANILLA": [
                {
                  "date": "2020-12-28", 
                  "datetime": "20201228", 
                  "filename": "Arrow-v10.0-ginkgo-OFFICIAL-20201228-VANILLA.zip", 
                  "filepath": "/arrow-10.0/ginkgo/Arrow-v10.0-ginkgo-OFFICIAL-20201228-VANILLA.zip", 
                  "sha256": "2899f99e2b52ce40afcf703376ebb48e3358fbb3b0567b93d15624e848119bbb", 
                  "size": "823680611", 
                  "type": "official", 
                  "version": "v10.0"
                }
              ]
            }
          ]
        }
      ], 
      "v11.0": [
        {
          "OFFICIAL": [
            {
              "GAPPS": [
                {
                  "date": "2021-01-15", 
                  "datetime": "20210115", 
                  "filename": "Arrow-v11.0-ginkgo-OFFICIAL-20210115-GAPPS.zip", 
                  "filepath": "/arrow-11.0/ginkgo/Arrow-v11.0-ginkgo-OFFICIAL-20210115-GAPPS.zip", 
                  "sha256": "15607eab86f59af516c0337851fad537b161bdabf421c85188a86b7e1182058e", 
                  "size": "1203280452", 
                  "type": "official", 
                  "version": "v11.0"
                }
              ], 
              "VANILLA": [
                {
                  "date": "2021-01-15", 
                  "datetime": "20210115", 
                  "filename": "Arrow-v11.0-ginkgo-OFFICIAL-20210115-VANILLA.zip", 
                  "filepath": "/arrow-11.0/ginkgo/Arrow-v11.0-ginkgo-OFFICIAL-20210115-VANILLA.zip", 
                  "sha256": "fd88c7668df42897c58f8997ead3563eca1c46ddd537a8fdd00e2a4b42082c90", 
                  "size": "883565419", 
                  "type": "official", 
                  "version": "v11.0"
                }
              ]
            }
          ], 
          "UNOFFICIAL": [
            {
              "GAPPS": [
                {
                  "date": "2020-12-28", 
                  "datetime": "20201228", 
                  "filename": "Arrow-v11.0-ginkgo-UNOFFICIAL-20201228-GAPPS.zip", 
                  "filepath": "/arrow-11.0/ginkgo/Arrow-v11.0-ginkgo-UNOFFICIAL-20201228-GAPPS.zip", 
                  "sha256": "8e15eeb314de5f8c2c4baa673186c1e98154d522112bad6c125d684f54780291", 
                  "size": "1198890882", 
                  "type": "unofficial", 
                  "version": "v11.0"
                }
              ]
            }
          ]
        }
      ]
    }
  ], 
  "jasmine_sprout": [
    {
      "changelog": "New clean trees", 
      "maintainer": "TG_DEVICE_MAINTAINER", 
      "model": "Mi A2", 
      "oem": "Xiaomi", 
      "v11.0": [
        {
          "COMMUNITY": [
            {
              "GAPPS": [
                {
                  "date": "2021-01-02", 
                  "datetime": "20210102", 
                  "filename": "Arrow-v11.0-jasmine_sprout-COMMUNITY-20210102-GAPPS.zip", 
                  "filepath": "/arrow-11.0/jasmine_sprout/Arrow-v11.0-jasmine_sprout-COMMUNITY-20210102-GAPPS.zip", 
                  "sha256": "64982ddf23e20d3cdcb13840a7cc1e78cde7073699aa2c0ec5b18b37741a5989", 
                  "size": "1134167429", 
                  "type": "community", 
                  "version": "v11.0"
                }
              ], 
              "VANILLA": [
                {
                  "date": "2021-01-02", 
                  "datetime": "20210102", 
                  "filename": "Arrow-v11.0-jasmine_sprout-COMMUNITY-20210102-VANILLA.zip", 
                  "filepath": "/arrow-11.0/jasmine_sprout/Arrow-v11.0-jasmine_sprout-COMMUNITY-20210102-VANILLA.zip", 
                  "sha256": "055f10dcda106b24148d7c7c6bda101c894dc3b64ed8e10caed22186b5bfd267", 
                  "size": "837696275", 
                  "type": "community", 
                  "version": "v11.0"
                }
              ]
            }
          ]
        }
      ]
    }
  ], 
  "land": [
    {
      "changelog": "-", 
      "maintainer": "Bauuuuu", 
      "model": "Redmi 3S", 
      "oem": "Xiaomi", 
      "v11.0": [
        {
          "OFFICIAL": [
            {
              "GAPPS": [
                {
                  "date": "2021-01-15", 
                  "datetime": "20210115", 
                  "filename": "Arrow-v11.0-land-OFFICIAL-20210115-GAPPS.zip", 
                  "filepath": "/arrow-11.0/land/Arrow-v11.0-land-OFFICIAL-20210115-GAPPS.zip", 
                  "sha256": "57c68bcb134eab14fd5b197f7c38b0b2de2ce9ad355d9f4467779f9f11e50726", 
                  "size": "1054950919", 
                  "type": "official", 
                  "version": "v11.0"
                }
              ], 
              "VANILLA": [
                {
                  "date": "2021-01-15", 
                  "datetime": "20210115", 
                  "filename": "Arrow-v11.0-land-OFFICIAL-20210115-VANILLA.zip", 
                  "filepath": "/arrow-11.0/land/Arrow-v11.0-land-OFFICIAL-20210115-VANILLA.zip", 
                  "sha256": "3447818e7da454a573ca6ec2b983f8795b2d5038bdbd339e328251e260d84344", 
                  "size": "739381468", 
                  "type": "official", 
                  "version": "v11.0"
                }
              ]
            }
          ], 
          "UNOFFICIAL": [
            {
              "GAPPS": [
                {
                  "date": "2020-12-12", 
                  "datetime": "20201212", 
                  "filename": "Arrow-v11.0-land-UNOFFICIAL-20201212-GAPPS.zip", 
                  "filepath": "/arrow-11.0/land/Arrow-v11.0-land-UNOFFICIAL-20201212-GAPPS.zip", 
                  "sha256": "f714fb304e3d76adee82ee9d8d484c542f052674d5309f933b369bd4632ff62f", 
                  "size": "1049517223", 
                  "type": "unofficial", 
                  "version": "v11.0"
                }
              ], 
              "VANILLA": [
                {
                  "date": "2020-12-30", 
                  "datetime": "20201230", 
                  "filename": "Arrow-v11.0-land-UNOFFICIAL-20201230-VANILLA.zip", 
                  "filepath": "/arrow-11.0/land/Arrow-v11.0-land-UNOFFICIAL-20201230-VANILLA.zip", 
                  "sha256": "8b6f31ab45b47df243c61c022f6348d040802441eae30331ddb47e199a08b91b", 
                  "size": "734782739", 
                  "type": "unofficial", 
                  "version": "v11.0"
                }
              ]
            }
          ]
        }
      ]
    }
  ], 
  "lavender": [
    {
      "changelog": "- Fixed Deepsleep\r\n- Redfin FP for January SPL\r\n- Predator-Stormbreaker HMP inline", 
      "maintainer": "Hazama25, ak940s", 
      "model": "Redmi Note 7", 
      "oem": "Xiaomi", 
      "v11.0": [
        {
          "COMMUNITY": [
            {
              "GAPPS": [
                {
                  "date": "2021-01-16", 
                  "datetime": "20210116", 
                  "filename": "Arrow-v11.0-lavender-COMMUNITY-20210116-GAPPS.zip", 
                  "filepath": "/arrow-11.0/lavender/Arrow-v11.0-lavender-COMMUNITY-20210116-GAPPS.zip", 
                  "sha256": "8bf5800b409c1c2e52ef2eab122df93a82758e5968fb0aaf7f8634c2f7737b4e", 
                  "size": "1251556706", 
                  "type": "community", 
                  "version": "v11.0"
                }
              ], 
              "VANILLA": [
                {
                  "date": "2021-01-15", 
                  "datetime": "20210115", 
                  "filename": "Arrow-v11.0-lavender-COMMUNITY-20210115-VANILLA.zip", 
                  "filepath": "/arrow-11.0/lavender/Arrow-v11.0-lavender-COMMUNITY-20210115-VANILLA.zip", 
                  "sha256": "29104a2d2e178a3251f4efd9aff2d4cf56901fe8ed4724ce237af7b9f3726352", 
                  "size": "935125771", 
                  "type": "community", 
                  "version": "v11.0"
                }
              ]
            }
          ]
        }
      ]
    }
  ], 
  "lmi": [
    {
      "changelog": "- Firmware and vendor require V12.2.1.0.RJKCNXM.\r\n\r\n- Device: https://github.com/ArrowOS-Devices/android_device_xiaomi_lmi/commits/arrow-11.0\r\n- Blobs: https://github.com/ArrowOS-Devices/android_vendor_xiaomi_lmi/commits/arrow-11.0", 
      "maintainer": "TH779, lamp216", 
      "model": "POCO F2 Pro", 
      "oem": "POCO", 
      "v10.0": [
        {
          "OFFICIAL": [
            {
              "GAPPS": [
                {
                  "date": "2020-12-27", 
                  "datetime": "20201227", 
                  "filename": "Arrow-v10.0-lmi-OFFICIAL-20201227-GAPPS.zip", 
                  "filepath": "/arrow-10.0/lmi/Arrow-v10.0-lmi-OFFICIAL-20201227-GAPPS.zip", 
                  "sha256": "3613f3b1f9132fe40c920ce8355e3efc43bb72c8406e690be18a1578a217e4a3", 
                  "size": "741013441", 
                  "type": "official", 
                  "version": "v10.0"
                }
              ], 
              "VANILLA": [
                {
                  "date": "2020-12-27", 
                  "datetime": "20201227", 
                  "filename": "Arrow-v10.0-lmi-OFFICIAL-20201227-VANILLA.zip", 
                  "filepath": "/arrow-10.0/lmi/Arrow-v10.0-lmi-OFFICIAL-20201227-VANILLA.zip", 
                  "sha256": "b89ab9bfc7c22e5843cd9ac226167958b78adbff5944b1eb8027568942341062", 
                  "size": "583188654", 
                  "type": "official", 
                  "version": "v10.0"
                }
              ]
            }
          ], 
          "UNOFFICIAL": [
            {
              "GAPPS": [
                {
                  "date": "2020-12-24", 
                  "datetime": "20201224", 
                  "filename": "Arrow-v10.0-lmi-UNOFFICIAL-20201224-GAPPS.zip", 
                  "filepath": "/arrow-10.0/lmi/Arrow-v10.0-lmi-UNOFFICIAL-20201224-GAPPS.zip", 
                  "sha256": "e661ad712669fbf7b0a156035519161fa32926e988f0bc59ab816906f46d6264", 
                  "size": "737523972", 
                  "type": "unofficial", 
                  "version": "v10.0"
                }
              ], 
              "VANILLA": [
                {
                  "date": "2020-11-26", 
                  "datetime": "20201126", 
                  "filename": "Arrow-v10.0-lmi-UNOFFICIAL-20201126-VANILLA.zip", 
                  "filepath": "/arrow-10.0/lmi/Arrow-v10.0-lmi-UNOFFICIAL-20201126-VANILLA.zip", 
                  "sha256": "9fdded032f5ed4dcc4d3df579bc09e5a9461e4c09d30e65f30f5d62d1eed15e0", 
                  "size": "600439606", 
                  "type": "unofficial", 
                  "version": "v10.0"
                }
              ]
            }
          ]
        }
      ], 
      "v11.0": [
        {
          "OFFICIAL": [
            {
              "GAPPS": [
                {
                  "date": "2021-01-15", 
                  "datetime": "20210115", 
                  "filename": "Arrow-v11.0-lmi-OFFICIAL-20210115-GAPPS.zip", 
                  "filepath": "/arrow-11.0/lmi/Arrow-v11.0-lmi-OFFICIAL-20210115-GAPPS.zip", 
                  "sha256": "92329d259b4f761dda6e095a756cf965e01dfc0223cf17995f6ab41e262a8891", 
                  "size": "1011266551", 
                  "type": "official", 
                  "version": "v11.0"
                }
              ], 
              "VANILLA": [
                {
                  "date": "2021-01-15", 
                  "datetime": "20210115", 
                  "filename": "Arrow-v11.0-lmi-OFFICIAL-20210115-VANILLA.zip", 
                  "filepath": "/arrow-11.0/lmi/Arrow-v11.0-lmi-OFFICIAL-20210115-VANILLA.zip", 
                  "sha256": "d5a06a2cf6d0552059f80c94472b02e4d562d89e5d3e298caa0c05b59be720ca", 
                  "size": "693496851", 
                  "type": "official", 
                  "version": "v11.0"
                }
              ]
            }
          ], 
          "UNOFFICIAL": [
            {
              "GAPPS": [
                {
                  "date": "2021-01-14", 
                  "datetime": "20210114", 
                  "filename": "Arrow-v11.0-lmi-UNOFFICIAL-20210114-GAPPS.zip", 
                  "filepath": "/arrow-11.0/lmi/Arrow-v11.0-lmi-UNOFFICIAL-20210114-GAPPS.zip", 
                  "sha256": "604ebeab82218ecd118968e3676684c28e691a9fe51abeb8b6874862b1672f29", 
                  "size": "1010165371", 
                  "type": "unofficial", 
                  "version": "v11.0"
                }
              ]
            }
          ]
        }
      ]
    }
  ], 
  "marlin": [
    {
      "changelog": null, 
      "maintainer": "blckbear", 
      "model": "Pixel XL", 
      "oem": "Google", 
      "v10.0": [
        {
          "UNOFFICIAL": [
            {
              "GAPPS": [
                {
                  "date": "2021-01-13", 
                  "datetime": "20210113", 
                  "filename": "Arrow-v10.0-marlin-UNOFFICIAL-20210113-GAPPS.zip", 
                  "filepath": "/arrow-10.0/marlin/Arrow-v10.0-marlin-UNOFFICIAL-20210113-GAPPS.zip", 
                  "sha256": "2a5a1a2129c8b3611a4e233fcf99ba1332db76024c6c0077588b3c300707b058", 
                  "size": "791132934", 
                  "type": "unofficial", 
                  "version": "v10.0"
                }
              ], 
              "VANILLA": [
                {
                  "date": "2021-01-13", 
                  "datetime": "20210113", 
                  "filename": "Arrow-v10.0-marlin-UNOFFICIAL-20210113-VANILLA.zip", 
                  "filepath": "/arrow-10.0/marlin/Arrow-v10.0-marlin-UNOFFICIAL-20210113-VANILLA.zip", 
                  "sha256": "02f0c3b70cc99b3a04a4a4174ac363e003f14ec7dcce672d94d1aa13c82216f6", 
                  "size": "578650284", 
                  "type": "unofficial", 
                  "version": "v10.0"
                }
              ]
            }
          ]
        }
      ]
    }
  ], 
  "miatoll": [
    {
      "changelog": "\u2022 Upstreamed kernel to 4.4.214\r\n\u2022 Fixed safetynet", 
      "maintainer": "SonalSingh18", 
      "model": "SM6250", 
      "oem": "Xiaomi", 
      "v11.0": [
        {
          "OFFICIAL": [
            {
              "GAPPS": [
                {
                  "date": "2021-01-15", 
                  "datetime": "20210115", 
                  "filename": "Arrow-v11.0-miatoll-OFFICIAL-20210115-GAPPS.zip", 
                  "filepath": "/arrow-11.0/miatoll/Arrow-v11.0-miatoll-OFFICIAL-20210115-GAPPS.zip", 
                  "sha256": "2cdc7522cf8661078d6798ee5e6823aad2b8a9a67cc8fea1c8908aee6ccce08a", 
                  "size": "1445053602", 
                  "type": "official", 
                  "version": "v11.0"
                }
              ], 
              "VANILLA": [
                {
                  "date": "2021-01-15", 
                  "datetime": "20210115", 
                  "filename": "Arrow-v11.0-miatoll-OFFICIAL-20210115-VANILLA.zip", 
                  "filepath": "/arrow-11.0/miatoll/Arrow-v11.0-miatoll-OFFICIAL-20210115-VANILLA.zip", 
                  "sha256": "29659ea5f4774c83579d7502d39fd41fda0382cb5ed44baea23f42557ae71c7f", 
                  "size": "1122500221", 
                  "type": "official", 
                  "version": "v11.0"
                }
              ]
            }
          ], 
          "UNOFFICIAL": [
            {
              "GAPPS": [
                {
                  "date": "2020-12-14", 
                  "datetime": "20201214", 
                  "filename": "Arrow-v11.0-miatoll-UNOFFICIAL-20201214-GAPPS.zip", 
                  "filepath": "/arrow-11.0/miatoll/Arrow-v11.0-miatoll-UNOFFICIAL-20201214-GAPPS.zip", 
                  "sha256": "5555810ca534191d851e52a6795028ef63a47859e783612f5f469c5128439bab", 
                  "size": "1440386752", 
                  "type": "unofficial", 
                  "version": "v11.0"
                }
              ], 
              "VANILLA": [
                {
                  "date": "2020-12-14", 
                  "datetime": "20201214", 
                  "filename": "Arrow-v11.0-miatoll-UNOFFICIAL-20201214-VANILLA.zip", 
                  "filepath": "/arrow-11.0/miatoll/Arrow-v11.0-miatoll-UNOFFICIAL-20201214-VANILLA.zip", 
                  "sha256": "447e2d6970dc22fe54b7cb56ed6d83db72479199f197a60695cbb2a63e893619", 
                  "size": "1112725715", 
                  "type": "unofficial", 
                  "version": "v11.0"
                }
              ]
            }
          ]
        }
      ]
    }
  ], 
  "mido": [
    {
      "changelog": "Note:\r\n- These are still going to continue on 3.18 builds only.\r\n- Requests for 4.9 builds will be ignored.\r\n\r\nThis decision has been taken as per the equal no.of requests from both sides of the parties and concluded by the outcome of adverse performance affects.", 
      "maintainer": "TG_DEVICE_MAINTAINER", 
      "model": "Redmi Note 4", 
      "oem": "Xiaomi", 
      "v11.0": [
        {
          "OFFICIAL": [
            {
              "GAPPS": [
                {
                  "date": "2021-01-16", 
                  "datetime": "20210116", 
                  "filename": "Arrow-v11.0-mido-OFFICIAL-20210116-GAPPS.zip", 
                  "filepath": "/arrow-11.0/mido/Arrow-v11.0-mido-OFFICIAL-20210116-GAPPS.zip", 
                  "sha256": "0297279be8e4e0fe5dc1ddf436f690943802737951d192a15948bd2d1efb359b", 
                  "size": "1035404798", 
                  "type": "official", 
                  "version": "v11.0"
                }
              ], 
              "VANILLA": [
                {
                  "date": "2021-01-15", 
                  "datetime": "20210115", 
                  "filename": "Arrow-v11.0-mido-OFFICIAL-20210115-VANILLA.zip", 
                  "filepath": "/arrow-11.0/mido/Arrow-v11.0-mido-OFFICIAL-20210115-VANILLA.zip", 
                  "sha256": "04b907f4b1a2c41b1e97b7274f441d678c624946fd0363a75489a799c1dd2846", 
                  "size": "719898037", 
                  "type": "official", 
                  "version": "v11.0"
                }
              ]
            }
          ]
        }
      ]
    }
  ], 
  "oneplus3": [
    {
      "changelog": "- Misc changes\r\n- BT Fix\r\n- Few SE Denials Defined\r\n- WhatsApp QR Code Fixed", 
      "maintainer": "Gaurav24", 
      "model": "OnePlus 3/3T", 
      "oem": "OnePlus", 
      "v11.0": [
        {
          "OFFICIAL": [
            {
              "GAPPS": [
                {
                  "date": "2021-01-15", 
                  "datetime": "20210115", 
                  "filename": "Arrow-v11.0-oneplus3-OFFICIAL-20210115-GAPPS.zip", 
                  "filepath": "/arrow-11.0/oneplus3/Arrow-v11.0-oneplus3-OFFICIAL-20210115-GAPPS.zip", 
                  "sha256": "b9791e674025143c754de0254906b2940655a38f11ddc4df9e2f63159778aff8", 
                  "size": "1054070871", 
                  "type": "official", 
                  "version": "v11.0"
                }
              ], 
              "VANILLA": [
                {
                  "date": "2021-01-15", 
                  "datetime": "20210115", 
                  "filename": "Arrow-v11.0-oneplus3-OFFICIAL-20210115-VANILLA.zip", 
                  "filepath": "/arrow-11.0/oneplus3/Arrow-v11.0-oneplus3-OFFICIAL-20210115-VANILLA.zip", 
                  "sha256": "f414502ab33dbc6b0f63ebad479f735f714967df616d5e559d9377ff9fbc8693", 
                  "size": "733063885", 
                  "type": "official", 
                  "version": "v11.0"
                }
              ]
            }
          ], 
          "UNOFFICIAL": [
            {
              "GAPPS": [
                {
                  "date": "2021-01-06", 
                  "datetime": "20210106", 
                  "filename": "Arrow-v11.0-oneplus3-UNOFFICIAL-20210106-GAPPS.zip", 
                  "filepath": "/arrow-11.0/oneplus3/Arrow-v11.0-oneplus3-UNOFFICIAL-20210106-GAPPS.zip", 
                  "sha256": "12d162771dceb9dcff2dc0f78d762eb478e64837c7df6bf5419413e54ca0c34d", 
                  "size": "1049176650", 
                  "type": "unofficial", 
                  "version": "v11.0"
                }
              ], 
              "VANILLA": [
                {
                  "date": "2021-01-06", 
                  "datetime": "20210106", 
                  "filename": "Arrow-v11.0-oneplus3-UNOFFICIAL-20210106-VANILLA.zip", 
                  "filepath": "/arrow-11.0/oneplus3/Arrow-v11.0-oneplus3-UNOFFICIAL-20210106-VANILLA.zip", 
                  "sha256": "d41b72da9867a34f8c1289743e7f3e340adaeaa8ef9a7e59a607d12b2c711567", 
                  "size": "728089040", 
                  "type": "unofficial", 
                  "version": "v11.0"
                }
              ]
            }
          ]
        }
      ]
    }
  ], 
  "perseus": [
    {
      "changelog": "!!!WARNING!!!\r\nRecommended clean flash\r\n\r\n- Update display, graphics, wfd and media blobs to R\r\n- Update display/audio/media hals to sdm710 R\r\n- Fixed WFD\r\n- Fixed \"Ok, Google\" with screen off\r\n- Switch to aidl Light HAL and update values\r\n- Switch Arrow kernel\r\n- Many fixes and upstream changes.\r\n\r\nNote:\r\n- It is required firmware part MIUI Q (Recommended V12.0.1.0).", 
      "maintainer": "palaych", 
      "model": "Mi MIX 3", 
      "oem": "Xiaomi", 
      "v11.0": [
        {
          "OFFICIAL": [
            {
              "GAPPS": [
                {
                  "date": "2021-01-14", 
                  "datetime": "20210114", 
                  "filename": "Arrow-v11.0-perseus-OFFICIAL-20210114-GAPPS.zip", 
                  "filepath": "/arrow-11.0/perseus/Arrow-v11.0-perseus-OFFICIAL-20210114-GAPPS.zip", 
                  "sha256": "bbec86a92bee304691f222b233e8eecb6d76e0313a217c314aaa295678f1438f", 
                  "size": "1338160994", 
                  "type": "official", 
                  "version": "v11.0"
                }
              ], 
              "VANILLA": [
                {
                  "date": "2021-01-14", 
                  "datetime": "20210114", 
                  "filename": "Arrow-v11.0-perseus-OFFICIAL-20210114-VANILLA.zip", 
                  "filepath": "/arrow-11.0/perseus/Arrow-v11.0-perseus-OFFICIAL-20210114-VANILLA.zip", 
                  "sha256": "5295297700ccc96735d8eb3a91207def9e510713f09005270366e2397054d327", 
                  "size": "1019324096", 
                  "type": "official", 
                  "version": "v11.0"
                }
              ]
            }
          ]
        }
      ]
    }
  ], 
  "phoenix": [
    {
      "changelog": "- Kernel upstreamed to 4.14.214\r\n- light: Properly scale brightness range\r\n- light: Avoid uint32_t underflow\r\n- decrease in-call volume a bit", 
      "maintainer": "Sreekanth", 
      "model": "POCO X2", 
      "oem": "POCO", 
      "v11.0": [
        {
          "OFFICIAL": [
            {
              "GAPPS": [
                {
                  "date": "2021-01-15", 
                  "datetime": "20210115", 
                  "filename": "Arrow-v11.0-phoenix-OFFICIAL-20210115-GAPPS.zip", 
                  "filepath": "/arrow-11.0/phoenix/Arrow-v11.0-phoenix-OFFICIAL-20210115-GAPPS.zip", 
                  "sha256": "f55dc9900fdb41c25f3f7feb3c8feb300d9f47c51491cc593ee85e0f27d14075", 
                  "size": "1025478879", 
                  "type": "official", 
                  "version": "v11.0"
                }
              ], 
              "VANILLA": [
                {
                  "date": "2021-01-15", 
                  "datetime": "20210115", 
                  "filename": "Arrow-v11.0-phoenix-OFFICIAL-20210115-VANILLA.zip", 
                  "filepath": "/arrow-11.0/phoenix/Arrow-v11.0-phoenix-OFFICIAL-20210115-VANILLA.zip", 
                  "sha256": "a3b6f7e6159b67268770123a66e26351fbddc822e331970a6a43112ab6401bad", 
                  "size": "705851506", 
                  "type": "official", 
                  "version": "v11.0"
                }
              ]
            }
          ], 
          "UNOFFICIAL": [
            {
              "GAPPS": [
                {
                  "date": "2021-01-09", 
                  "datetime": "20210109", 
                  "filename": "Arrow-v11.0-phoenix-UNOFFICIAL-20210109-GAPPS.zip", 
                  "filepath": "/arrow-11.0/phoenix/Arrow-v11.0-phoenix-UNOFFICIAL-20210109-GAPPS.zip", 
                  "sha256": "045191e3978754946b3786f88669a7251b8bdf353cac3fd983676835bf660f86", 
                  "size": "1021438406", 
                  "type": "unofficial", 
                  "version": "v11.0"
                }
              ], 
              "VANILLA": [
                {
                  "date": "2021-01-09", 
                  "datetime": "20210109", 
                  "filename": "Arrow-v11.0-phoenix-UNOFFICIAL-20210109-VANILLA.zip", 
                  "filepath": "/arrow-11.0/phoenix/Arrow-v11.0-phoenix-UNOFFICIAL-20210109-VANILLA.zip", 
                  "sha256": "0b2752cf3a00908c661288cd62e600090b3f9521a6b14e2243eebf1e422b8c0a", 
                  "size": "701931190", 
                  "type": "unofficial", 
                  "version": "v11.0"
                }
              ]
            }
          ]
        }
      ]
    }
  ], 
  "polaris": [
    {
      "changelog": "!!!WARNING!!!\r\nREQUEST ONLY CLEAN FLASH\r\n\r\n- Enable force encryption\r\n- Update display, graphics, wfd and media blobs to R\r\n- Update display/audio/media hals to sdm710 R\r\n- Fixed WFD\r\n- Fixed \"Ok, Google\" with screen off\r\n- Switch to aidl Light HAL and update values\r\n- Many fixes and upstream changes.\r\n\r\nNote:\r\n- From now on it is required to be on Q firmware (11.0.3.0 global or more new)\r\n- Don`t flash on previous build dirty, will bootloop and drop data.", 
      "maintainer": "palaych", 
      "model": "Mi MIX 2S", 
      "oem": "Xiaomi", 
      "v10.0": [
        {
          "OFFICIAL": [
            {
              "GAPPS": [
                {
                  "date": "2020-12-27", 
                  "datetime": "20201227", 
                  "filename": "Arrow-v10.0-polaris-OFFICIAL-20201227-GAPPS.zip", 
                  "filepath": "/arrow-10.0/polaris/Arrow-v10.0-polaris-OFFICIAL-20201227-GAPPS.zip", 
                  "sha256": "5ee9791c9da5d3212a1641468566a538dae80eea64045a0648aa06bb300525e1", 
                  "size": "952016585", 
                  "type": "official", 
                  "version": "v10.0"
                }
              ], 
              "VANILLA": [
                {
                  "date": "2020-12-27", 
                  "datetime": "20201227", 
                  "filename": "Arrow-v10.0-polaris-OFFICIAL-20201227-VANILLA.zip", 
                  "filepath": "/arrow-10.0/polaris/Arrow-v10.0-polaris-OFFICIAL-20201227-VANILLA.zip", 
                  "sha256": "0581162a2693cd4382c06ea1f7c4205d5e45090f7ef6e5927ade4218ff5272d7", 
                  "size": "793068078", 
                  "type": "official", 
                  "version": "v10.0"
                }
              ]
            }
          ]
        }
      ], 
      "v11.0": [
        {
          "OFFICIAL": [
            {
              "GAPPS": [
                {
                  "date": "2021-01-14", 
                  "datetime": "20210114", 
                  "filename": "Arrow-v11.0-polaris-OFFICIAL-20210114-GAPPS.zip", 
                  "filepath": "/arrow-11.0/polaris/Arrow-v11.0-polaris-OFFICIAL-20210114-GAPPS.zip", 
                  "sha256": "8f8d16cc751a1a5c1f5a63172a05c9faccc3392bfc4db8632e74beb08abe0952", 
                  "size": "1207999114", 
                  "type": "official", 
                  "version": "v11.0"
                }
              ], 
              "VANILLA": [
                {
                  "date": "2021-01-14", 
                  "datetime": "20210114", 
                  "filename": "Arrow-v11.0-polaris-OFFICIAL-20210114-VANILLA.zip", 
                  "filepath": "/arrow-11.0/polaris/Arrow-v11.0-polaris-OFFICIAL-20210114-VANILLA.zip", 
                  "sha256": "f3e5a4dd6cad3e5189ddbdfc215c45be0b8bd9094c312b0a27a1df386ebb9400", 
                  "size": "891795219", 
                  "type": "official", 
                  "version": "v11.0"
                }
              ]
            }
          ]
        }
      ]
    }
  ], 
  "potter": [
    {
      "changelog": "- misc", 
      "maintainer": "kubersharma001", 
      "model": "Moto G5 Plus", 
      "oem": "motorola", 
      "v10.0": [
        {
          "OFFICIAL": [
            {
              "GAPPS": [
                {
                  "date": "2021-01-02", 
                  "datetime": "20210102", 
                  "filename": "Arrow-v10.0-potter-OFFICIAL-20210102-GAPPS.zip", 
                  "filepath": "/arrow-10.0/potter/Arrow-v10.0-potter-OFFICIAL-20210102-GAPPS.zip", 
                  "sha256": "56cd105ddc33d9aad01df2767c392b656d356426c0bd44a49f9d4a244a67c499", 
                  "size": "812319370", 
                  "type": "official", 
                  "version": "v10.0"
                }
              ], 
              "VANILLA": [
                {
                  "date": "2021-01-02", 
                  "datetime": "20210102", 
                  "filename": "Arrow-v10.0-potter-OFFICIAL-20210102-VANILLA.zip", 
                  "filepath": "/arrow-10.0/potter/Arrow-v10.0-potter-OFFICIAL-20210102-VANILLA.zip", 
                  "sha256": "b321cb3df1dd212ed1e3bce27768832746b1661a2833f533e58d371e6fd5ec03", 
                  "size": "657580586", 
                  "type": "official", 
                  "version": "v10.0"
                }
              ]
            }
          ]
        }
      ], 
      "v11.0": [
        {
          "COMMUNITY": [
            {
              "GAPPS": [
                {
                  "date": "2020-11-22", 
                  "datetime": "20201122", 
                  "filename": "Arrow-v11.0-potter-COMMUNITY-20201122-GAPPS.zip", 
                  "filepath": "/arrow-11.0/potter/Arrow-v11.0-potter-COMMUNITY-20201122-GAPPS.zip", 
                  "sha256": "745e9ed1e5201185181280ed56f2e9c7890524f66bb62f427ff6bd5fbb8d62b5", 
                  "size": "952747427", 
                  "type": "community", 
                  "version": "v11.0"
                }
              ], 
              "VANILLA": [
                {
                  "date": "2020-11-22", 
                  "datetime": "20201122", 
                  "filename": "Arrow-v11.0-potter-COMMUNITY-20201122-VANILLA.zip", 
                  "filepath": "/arrow-11.0/potter/Arrow-v11.0-potter-COMMUNITY-20201122-VANILLA.zip", 
                  "sha256": "4696433e52aa7c8171029dc81136c16ed4f7e171012fac0abb6d9d280711fb05", 
                  "size": "742477510", 
                  "type": "community", 
                  "version": "v11.0"
                }
              ]
            }
          ]
        }
      ]
    }
  ], 
  "raphael": [
    {
      "changelog": null, 
      "maintainer": "kubersharma001", 
      "model": "Redmi K20 Pro", 
      "oem": "Xiaomi", 
      "v10.0": [
        {
          "OFFICIAL": [
            {
              "GAPPS": [
                {
                  "date": "2020-12-31", 
                  "datetime": "20201231", 
                  "filename": "Arrow-v10.0-raphael-OFFICIAL-20201231-GAPPS.zip", 
                  "filepath": "/arrow-10.0/raphael/Arrow-v10.0-raphael-OFFICIAL-20201231-GAPPS.zip", 
                  "sha256": "753459ae88413ba6ff61230cd37ffffc518675218a5e04cad0e73473e42bde63", 
                  "size": "747289253", 
                  "type": "official", 
                  "version": "v10.0"
                }
              ], 
              "VANILLA": [
                {
                  "date": "2020-12-31", 
                  "datetime": "20201231", 
                  "filename": "Arrow-v10.0-raphael-OFFICIAL-20201231-VANILLA.zip", 
                  "filepath": "/arrow-10.0/raphael/Arrow-v10.0-raphael-OFFICIAL-20201231-VANILLA.zip", 
                  "sha256": "04e3c9a3b0f9938e33541af074b165a7300dcbbcb0115d7a0222da0650a0082d", 
                  "size": "590355847", 
                  "type": "official", 
                  "version": "v10.0"
                }
              ]
            }
          ]
        }
      ], 
      "v11.0": [
        {
          "OFFICIAL": [
            {
              "GAPPS": [
                {
                  "date": "2021-01-15", 
                  "datetime": "20210115", 
                  "filename": "Arrow-v11.0-raphael-OFFICIAL-20210115-GAPPS.zip", 
                  "filepath": "/arrow-11.0/raphael/Arrow-v11.0-raphael-OFFICIAL-20210115-GAPPS.zip", 
                  "sha256": "8a3ac1324f7ce04120552e676b3c9c28fa0a9b040ba63c5eae8c3b4989b633a2", 
                  "size": "1017871379", 
                  "type": "official", 
                  "version": "v11.0"
                }
              ], 
              "VANILLA": [
                {
                  "date": "2021-01-15", 
                  "datetime": "20210115", 
                  "filename": "Arrow-v11.0-raphael-OFFICIAL-20210115-VANILLA.zip", 
                  "filepath": "/arrow-11.0/raphael/Arrow-v11.0-raphael-OFFICIAL-20210115-VANILLA.zip", 
                  "sha256": "d6e7584a0e9fdd412908c406255f52e5d3a7423af632e6eb723f58181a7bfe75", 
                  "size": "703295875", 
                  "type": "official", 
                  "version": "v11.0"
                }
              ]
            }
          ], 
          "UNOFFICIAL": [
            {
              "GAPPS": [
                {
                  "date": "2020-11-22", 
                  "datetime": "20201122", 
                  "filename": "Arrow-v11.0-raphael-UNOFFICIAL-20201122-GAPPS.zip", 
                  "filepath": "/arrow-11.0/raphael/Arrow-v11.0-raphael-UNOFFICIAL-20201122-GAPPS.zip", 
                  "sha256": "5d8c80594afeec4c10b7ad16fb790ba466dff4542ed555370db7434a9da04901", 
                  "size": "938076664", 
                  "type": "unofficial", 
                  "version": "v11.0"
                }
              ], 
              "VANILLA": [
                {
                  "date": "2020-11-22", 
                  "datetime": "20201122", 
                  "filename": "Arrow-v11.0-raphael-UNOFFICIAL-20201122-VANILLA.zip", 
                  "filepath": "/arrow-11.0/raphael/Arrow-v11.0-raphael-UNOFFICIAL-20201122-VANILLA.zip", 
                  "sha256": "9559d200afe947a9a394e86f68926d9799601874c4d20556a6aaa38ccd5fabc1", 
                  "size": "690802068", 
                  "type": "unofficial", 
                  "version": "v11.0"
                }
              ]
            }
          ]
        }
      ]
    }
  ], 
  "sailfish": [
    {
      "changelog": null, 
      "maintainer": "blckbear", 
      "model": "Pixel", 
      "oem": "Google", 
      "v10.0": [
        {
          "UNOFFICIAL": [
            {
              "GAPPS": [
                {
                  "date": "2021-01-13", 
                  "datetime": "20210113", 
                  "filename": "Arrow-v10.0-sailfish-UNOFFICIAL-20210113-GAPPS.zip", 
                  "filepath": "/arrow-10.0/sailfish/Arrow-v10.0-sailfish-UNOFFICIAL-20210113-GAPPS.zip", 
                  "sha256": "418644efd9038d3d5681361995679f02b52b46db2362d46272f4c19518eeb5be", 
                  "size": "791089022", 
                  "type": "unofficial", 
                  "version": "v10.0"
                }
              ], 
              "VANILLA": [
                {
                  "date": "2021-01-13", 
                  "datetime": "20210113", 
                  "filename": "Arrow-v10.0-sailfish-UNOFFICIAL-20210113-VANILLA.zip", 
                  "filepath": "/arrow-10.0/sailfish/Arrow-v10.0-sailfish-UNOFFICIAL-20210113-VANILLA.zip", 
                  "sha256": "eda588c0a6ba6f8ba2775440b40c1a79f3f24312237577f53235ae7543756c36", 
                  "size": "577579993", 
                  "type": "unofficial", 
                  "version": "v10.0"
                }
              ]
            }
          ]
        }
      ]
    }
  ], 
  "sanders": [
    {
      "changelog": "Clean flash must (kindly backup your data before flashing)\r\nimproved  performance\r\nEnabled ZRAM by default\r\nTuned ZRAM for better performance\r\nCompiled with hwui for better performance\r\nSwitched to Mad Kernel 2.0", 
      "maintainer": "Ashwatthama", 
      "model": "Moto G (5S) Plus", 
      "oem": "motorola", 
      "v10.0": [
        {
          "OFFICIAL": [
            {
              "GAPPS": [
                {
                  "date": "2020-12-28", 
                  "datetime": "20201228", 
                  "filename": "Arrow-v10.0-sanders-OFFICIAL-20201228-GAPPS.zip", 
                  "filepath": "/arrow-10.0/sanders/Arrow-v10.0-sanders-OFFICIAL-20201228-GAPPS.zip", 
                  "sha256": "8cc583d47724cc3e2f5a0231986a5e73e469b3cd760fad90589dd648dee930ce", 
                  "size": "783647404", 
                  "type": "official", 
                  "version": "v10.0"
                }
              ], 
              "VANILLA": [
                {
                  "date": "2020-12-28", 
                  "datetime": "20201228", 
                  "filename": "Arrow-v10.0-sanders-OFFICIAL-20201228-VANILLA.zip", 
                  "filepath": "/arrow-10.0/sanders/Arrow-v10.0-sanders-OFFICIAL-20201228-VANILLA.zip", 
                  "sha256": "bfbd05893f94d44d8b1af3d5fc96f519ee19249fac26e87605231b91e1dcdcb5", 
                  "size": "628362181", 
                  "type": "official", 
                  "version": "v10.0"
                }
              ]
            }
          ]
        }
      ], 
      "v11.0": [
        {
          "OFFICIAL": [
            {
              "GAPPS": [
                {
                  "date": "2021-01-16", 
                  "datetime": "20210116", 
                  "filename": "Arrow-v11.0-sanders-OFFICIAL-20210116-GAPPS.zip", 
                  "filepath": "/arrow-11.0/sanders/Arrow-v11.0-sanders-OFFICIAL-20210116-GAPPS.zip", 
                  "sha256": "fbde5501c674fc6e2ebb9e3977fa21f82c6458aaf8a57234942806af25b9a59d", 
                  "size": "1071096393", 
                  "type": "official", 
                  "version": "v11.0"
                }
              ], 
              "VANILLA": [
                {
                  "date": "2021-01-16", 
                  "datetime": "20210116", 
                  "filename": "Arrow-v11.0-sanders-OFFICIAL-20210116-VANILLA.zip", 
                  "filepath": "/arrow-11.0/sanders/Arrow-v11.0-sanders-OFFICIAL-20210116-VANILLA.zip", 
                  "sha256": "a5e869dac350d1cdb1661364c470fc9f80e4aa227a8389b41d70409fecf14b1e", 
                  "size": "756192802", 
                  "type": "official", 
                  "version": "v11.0"
                }
              ]
            }
          ], 
          "UNOFFICIAL": [
            {
              "GAPPS": [
                {
                  "date": "2021-01-01", 
                  "datetime": "20210101", 
                  "filename": "Arrow-v11.0-sanders-UNOFFICIAL-20210101-GAPPS.zip", 
                  "filepath": "/arrow-11.0/sanders/Arrow-v11.0-sanders-UNOFFICIAL-20210101-GAPPS.zip", 
                  "sha256": "4ee85d51e7b6028c56fa2f08e7457eefe56a344f5e5f2a44de2dab973c4f2292", 
                  "size": "1065640230", 
                  "type": "unofficial", 
                  "version": "v11.0"
                }
              ], 
              "VANILLA": [
                {
                  "date": "2021-01-06", 
                  "datetime": "20210106", 
                  "filename": "Arrow-v11.0-sanders-UNOFFICIAL-20210106-VANILLA.zip", 
                  "filepath": "/arrow-11.0/sanders/Arrow-v11.0-sanders-UNOFFICIAL-20210106-VANILLA.zip", 
                  "sha256": "b59ec2019bc800c0bd9c82a2459ab1e8b9c6c8de2e99261cb1c0211e102a01ce", 
                  "size": "754995816", 
                  "type": "unofficial", 
                  "version": "v11.0"
                }
              ]
            }
          ]
        }
      ]
    }
  ], 
  "surya": [
    {
      "changelog": "- Performance improvements & enhancements\r\n- Switch to latest caf tag upstreamed kernel\r\n- Upstream blobs from MIUI V12.0.8.0.QJGINXM \r\n- Add proper notch masking overlay to hide camera cutout\r\n- Fix crackling noise while playing some sounds\r\n- Adjust brightness values\r\n- Revamp and organize tree\r\n- Dynamically set power profile according to device model\r\n- Update power HAL to support hints\r\n- Improve and optimize wifi conf\r\n- Performance/Optimization related props\r\n- Added clear speaker option\r\n- Refine parts with updated icons and strings\r\n- Doze functionality improvements\r\n- More translations dump for parts\r\n- Misc fixes and changes\r\n\r\nNote:\r\n- Unified builds", 
      "maintainer": "Ganesh Varma", 
      "model": "POCO X3 NFC", 
      "oem": "POCO", 
      "v11.0": [
        {
          "OFFICIAL": [
            {
              "GAPPS": [
                {
                  "date": "2021-01-15", 
                  "datetime": "20210115", 
                  "filename": "Arrow-v11.0-surya-OFFICIAL-20210115-GAPPS.zip", 
                  "filepath": "/arrow-11.0/surya/Arrow-v11.0-surya-OFFICIAL-20210115-GAPPS.zip", 
                  "sha256": "430b8a7ea85f431b9d75e6253ef9acd3a5a0d6cd04ecdee6be3ca779b3ecc040", 
                  "size": "1006284908", 
                  "type": "official", 
                  "version": "v11.0"
                }
              ], 
              "VANILLA": [
                {
                  "date": "2021-01-15", 
                  "datetime": "20210115", 
                  "filename": "Arrow-v11.0-surya-OFFICIAL-20210115-VANILLA.zip", 
                  "filepath": "/arrow-11.0/surya/Arrow-v11.0-surya-OFFICIAL-20210115-VANILLA.zip", 
                  "sha256": "d019d9178e1e2f7314e7e6206cd78a22f25997380627ad8b7945a99647f36e87", 
                  "size": "687381636", 
                  "type": "official", 
                  "version": "v11.0"
                }
              ]
            }
          ]
        }
      ]
    }
  ], 
  "violet": [
    {
      "changelog": "NOTE: Clean flash Recommended\r\n\r\nCHANGELOGS\r\n- Switched to R Hals\r\n- Enabled Gralloc 4\r\n- Updated almost every vendor blobs to R\r\n- Dropped prebuilt kernel\r\n- USB Fatcharge is back in violet parts\r\n- Fixed idle drains\r\n- Fixed Wifi and Hotspot problems\r\n- No more crashes with GCam 8\r\n- CTS pass out of the box without root\r\n- Merged LA.UM.9.1.r1-08300-SMxxx0.0 tag in the kernel\r\n- Lots of Audio and Media Playback improvements\r\n- Bug related to IR blaster is fixed\r\n- Many performance improvements and bug fixes\r\n- For more check trees\r\n\r\nKNOWN BUGS\r\n- FM Radio\r\n- SELinux status in violet parts", 
      "maintainer": "Aftab Ashrafi", 
      "model": "Redmi Note 7 Pro", 
      "oem": "Xiaomi", 
      "v11.0": [
        {
          "OFFICIAL": [
            {
              "GAPPS": [
                {
                  "date": "2021-01-15", 
                  "datetime": "20210115", 
                  "filename": "Arrow-v11.0-violet-OFFICIAL-20210115-GAPPS.zip", 
                  "filepath": "/arrow-11.0/violet/Arrow-v11.0-violet-OFFICIAL-20210115-GAPPS.zip", 
                  "sha256": "382dd7e89b3c698e5fcbd357f055e73fa9aa9bb9deddb329100d4d8ded509981", 
                  "size": "1276549650", 
                  "type": "official", 
                  "version": "v11.0"
                }
              ], 
              "VANILLA": [
                {
                  "date": "2021-01-15", 
                  "datetime": "20210115", 
                  "filename": "Arrow-v11.0-violet-OFFICIAL-20210115-VANILLA.zip", 
                  "filepath": "/arrow-11.0/violet/Arrow-v11.0-violet-OFFICIAL-20210115-VANILLA.zip", 
                  "sha256": "454296fe5e31a2512501e80fb134c6448c8581aad467961f82a6f8daad852e2a", 
                  "size": "957745069", 
                  "type": "official", 
                  "version": "v11.0"
                }
              ]
            }
          ], 
          "UNOFFICIAL": [
            {
              "GAPPS": [
                {
                  "date": "2021-01-11", 
                  "datetime": "20210111", 
                  "filename": "Arrow-v11.0-violet-UNOFFICIAL-20210111-GAPPS.zip", 
                  "filepath": "/arrow-11.0/violet/Arrow-v11.0-violet-UNOFFICIAL-20210111-GAPPS.zip", 
                  "sha256": "1a6ac6857daa74016e097669911d6c53fa94f86cdd04bf7dbcc3c22456b01123", 
                  "size": "1258439842", 
                  "type": "unofficial", 
                  "version": "v11.0"
                }
              ], 
              "VANILLA": [
                {
                  "date": "2021-01-10", 
                  "datetime": "20210110", 
                  "filename": "Arrow-v11.0-violet-UNOFFICIAL-20210110-VANILLA.zip", 
                  "filepath": "/arrow-11.0/violet/Arrow-v11.0-violet-UNOFFICIAL-20210110-VANILLA.zip", 
                  "sha256": "a02cc914432e01db7359e8ac93110d49671702cb53d6d3a6cc6f34e91c6eb3b6", 
                  "size": "939681768", 
                  "type": "unofficial", 
                  "version": "v11.0"
                }
              ]
            }
          ]
        }
      ]
    }
  ], 
  "wayne": [
    {
      "changelog": null, 
      "maintainer": "TH779", 
      "model": "MI 6X", 
      "oem": "Xiaomi", 
      "v11.0": [
        {
          "OFFICIAL": [
            {
              "GAPPS": [
                {
                  "date": "2021-01-15", 
                  "datetime": "20210115", 
                  "filename": "Arrow-v11.0-wayne-OFFICIAL-20210115-GAPPS.zip", 
                  "filepath": "/arrow-11.0/wayne/Arrow-v11.0-wayne-OFFICIAL-20210115-GAPPS.zip", 
                  "sha256": "8960ff3ae6268e697ea3a67d740446cc6f6bd06b13fb6782679199e4a89449e7", 
                  "size": "1107449975", 
                  "type": "official", 
                  "version": "v11.0"
                }
              ], 
              "VANILLA": [
                {
                  "date": "2021-01-15", 
                  "datetime": "20210115", 
                  "filename": "Arrow-v11.0-wayne-OFFICIAL-20210115-VANILLA.zip", 
                  "filepath": "/arrow-11.0/wayne/Arrow-v11.0-wayne-OFFICIAL-20210115-VANILLA.zip", 
                  "sha256": "4a6aad26d80379b209453e7f3b77192cfb97a1573c36ed7c55fd9f3b82f8084e", 
                  "size": "781994869", 
                  "type": "official", 
                  "version": "v11.0"
                }
              ]
            }
          ], 
          "UNOFFICIAL": [
            {
              "GAPPS": [
                {
                  "date": "2020-12-31", 
                  "datetime": "20201231", 
                  "filename": "Arrow-v11.0-wayne-UNOFFICIAL-20201231-GAPPS.zip", 
                  "filepath": "/arrow-11.0/wayne/Arrow-v11.0-wayne-UNOFFICIAL-20201231-GAPPS.zip", 
                  "sha256": "0c41a90186a11ef3164fe8b60a0592b5c162ac1fc6960805a8aaef0f72dd4cd2", 
                  "size": "1103521546", 
                  "type": "unofficial", 
                  "version": "v11.0"
                }
              ]
            }
          ]
        }
      ]
    }
  ], 
  "whyred": [
    {
      "changelog": "- SELinux enforcing\r\n- Drop deprecated android.hardware.thermal HAL\r\n- Switch to QTI thermal 2.0 hal\r\n- Add shim for libdpmframework\r\n- Build libhidltransport/libhwbinder from source\r\n- Kernel upstreamed to Linux version 4.4.251\r\n- Misc changes", 
      "maintainer": "Sreekanth", 
      "model": "Redmi Note 5", 
      "oem": "Xiaomi", 
      "v10.0": [
        {
          "OFFICIAL": [
            {
              "GAPPS": [
                {
                  "date": "2020-12-27", 
                  "datetime": "20201227", 
                  "filename": "Arrow-v10.0-whyred-OFFICIAL-20201227-GAPPS.zip", 
                  "filepath": "/arrow-10.0/whyred/Arrow-v10.0-whyred-OFFICIAL-20201227-GAPPS.zip", 
                  "sha256": "48deacdc86684220e760b58a39c27906e00d1239dac45f4da3e663d70afafe7c", 
                  "size": "851077402", 
                  "type": "official", 
                  "version": "v10.0"
                }
              ], 
              "VANILLA": [
                {
                  "date": "2020-12-27", 
                  "datetime": "20201227", 
                  "filename": "Arrow-v10.0-whyred-OFFICIAL-20201227-VANILLA.zip", 
                  "filepath": "/arrow-10.0/whyred/Arrow-v10.0-whyred-OFFICIAL-20201227-VANILLA.zip", 
                  "sha256": "fadd3f9006c9870b2ee10a51f5e0d577cb7808588a364b88e4e1b6207a72d254", 
                  "size": "695816906", 
                  "type": "official", 
                  "version": "v10.0"
                }
              ]
            }
          ]
        }
      ], 
      "v11.0": [
        {
          "OFFICIAL": [
            {
              "GAPPS": [
                {
                  "date": "2021-01-15", 
                  "datetime": "20210115", 
                  "filename": "Arrow-v11.0-whyred-OFFICIAL-20210115-GAPPS.zip", 
                  "filepath": "/arrow-11.0/whyred/Arrow-v11.0-whyred-OFFICIAL-20210115-GAPPS.zip", 
                  "sha256": "f0ea500c445fac815da468096ad94dc0dd24bcd8e1436053c87e3daa9dbe1c36", 
                  "size": "1108656984", 
                  "type": "official", 
                  "version": "v11.0"
                }
              ], 
              "VANILLA": [
                {
                  "date": "2021-01-15", 
                  "datetime": "20210115", 
                  "filename": "Arrow-v11.0-whyred-OFFICIAL-20210115-VANILLA.zip", 
                  "filepath": "/arrow-11.0/whyred/Arrow-v11.0-whyred-OFFICIAL-20210115-VANILLA.zip", 
                  "sha256": "61e76e549fcc2f8c52f7e4b4517c38bf32abcb95ddd5f9e7989a62760bbd879b", 
                  "size": "793446590", 
                  "type": "official", 
                  "version": "v11.0"
                }
              ]
            }
          ], 
          "UNOFFICIAL": [
            {
              "GAPPS": [
                {
                  "date": "2020-12-14", 
                  "datetime": "20201214", 
                  "filename": "Arrow-v11.0-whyred-UNOFFICIAL-20201214-GAPPS.zip", 
                  "filepath": "/arrow-11.0/whyred/Arrow-v11.0-whyred-UNOFFICIAL-20201214-GAPPS.zip", 
                  "sha256": "d531131340f3e460b10cb6b0686759d822428c2693985cf2959bf60908a8f0a8", 
                  "size": "1102489644", 
                  "type": "unofficial", 
                  "version": "v11.0"
                }
              ], 
              "VANILLA": [
                {
                  "date": "2021-01-15", 
                  "datetime": "20210115", 
                  "filename": "Arrow-v11.0-whyred-UNOFFICIAL-20210115-VANILLA.zip", 
                  "filepath": "/arrow-11.0/whyred/Arrow-v11.0-whyred-UNOFFICIAL-20210115-VANILLA.zip", 
                  "sha256": "8f7c89a64f2028627bc900e6cdea6a885e7850edc4bc34b81d9a4f50bc419fd6", 
                  "size": "787989865", 
                  "type": "unofficial", 
                  "version": "v11.0"
                }
              ]
            }
          ]
        }
      ]
    }
  ], 
  "z2_plus": [
    {
      "changelog": "-", 
      "maintainer": "kubersharma001", 
      "model": "Z2 Plus", 
      "oem": "ZUK", 
      "v10.0": [
        {
          "OFFICIAL": [
            {
              "GAPPS": [
                {
                  "date": "2020-12-27", 
                  "datetime": "20201227", 
                  "filename": "Arrow-v10.0-z2_plus-OFFICIAL-20201227-GAPPS.zip", 
                  "filepath": "/arrow-10.0/z2_plus/Arrow-v10.0-z2_plus-OFFICIAL-20201227-GAPPS.zip", 
                  "sha256": "4a39fd021f4f56957d1732eb1a4681753293e0e3659cb99e719866a7fbce365c", 
                  "size": "815312408", 
                  "type": "official", 
                  "version": "v10.0"
                }
              ], 
              "VANILLA": [
                {
                  "date": "2020-12-27", 
                  "datetime": "20201227", 
                  "filename": "Arrow-v10.0-z2_plus-OFFICIAL-20201227-VANILLA.zip", 
                  "filepath": "/arrow-10.0/z2_plus/Arrow-v10.0-z2_plus-OFFICIAL-20201227-VANILLA.zip", 
                  "sha256": "517131b6b0307fc87dcbb1eaee0b4d9f37ce43ca9128cb7398d5911a17e380a6", 
                  "size": "659114951", 
                  "type": "official", 
                  "version": "v10.0"
                }
              ]
            }
          ]
        }
      ]
    }
  ], 
  "z2_row": [
    {
      "changelog": "-", 
      "maintainer": "kubersharma001, weimerd", 
      "model": "ZUK Z2121", 
      "oem": "ZUK", 
      "v10.0": [
        {
          "OFFICIAL": [
            {
              "GAPPS": [
                {
                  "date": "2020-12-28", 
                  "datetime": "20201228", 
                  "filename": "Arrow-v10.0-z2_row-OFFICIAL-20201228-GAPPS.zip", 
                  "filepath": "/arrow-10.0/z2_row/Arrow-v10.0-z2_row-OFFICIAL-20201228-GAPPS.zip", 
                  "sha256": "7bc930477ee1192aa879aaaf81691392b57ef71d817fd72fb58c7e37dc328cbb", 
                  "size": "815451131", 
                  "type": "official", 
                  "version": "v10.0"
                }
              ], 
              "VANILLA": [
                {
                  "date": "2020-12-27", 
                  "datetime": "20201227", 
                  "filename": "Arrow-v10.0-z2_row-OFFICIAL-20201227-VANILLA.zip", 
                  "filepath": "/arrow-10.0/z2_row/Arrow-v10.0-z2_row-OFFICIAL-20201227-VANILLA.zip", 
                  "sha256": "4a8e69d1f133acb675694aa77df29454312c6ce3e5afbf1c2bbde8571e53396c", 
                  "size": "659241854", 
                  "type": "official", 
                  "version": "v10.0"
                }
              ]
            }
          ]
        }
      ]
    }
  ]
}