{
    "G": [
        {
            "changelog": null, 
            "date": "2022-03-24", 
            "datetime": "20220324", 
            "filename": "Arrow-v12.1-G-OFFICIAL-20220324-VANILLA.zip", 
            "filepath": "/arrow-12.1/G/Arrow-v12.1-G-OFFICIAL-20220324-VANILLA.zip", 
            "maintainer": "kardebayan", 
            "model": "10or G", 
            "oem": "10or", 
            "sha256": "4b4bc9702b6a6b0dae010740f41471143fb29f0c2067f63f6511e807e2e70def", 
            "size": "688235188", 
            "type": "official", 
            "version": "v12.1"
        }
    ], 
    "RMX1801": [
        {
            "changelog": null, 
            "date": "2022-04-16", 
            "datetime": "20220416", 
            "filename": "Arrow-v12.1-RMX1801-OFFICIAL-20220416-VANILLA.zip", 
            "filepath": "/arrow-12.1/RMX1801/Arrow-v12.1-RMX1801-OFFICIAL-20220416-VANILLA.zip", 
            "maintainer": "Baibhab", 
            "model": "Realme 2 Pro", 
            "oem": "oppo", 
            "sha256": "d30052938079b031b3c1ffdbdef316989ebc8ae97b6850c8344c91c270cd635a", 
            "size": "997645273", 
            "type": "official", 
            "version": "v12.1"
        }
    ], 
    "RMX2020": [
        {
            "changelog": "NOTE: For Realme UI 1.0 FW only.", 
            "date": "2022-04-16", 
            "datetime": "20220416", 
            "filename": "Arrow-v12.1-RMX2020-OFFICIAL-20220416-VANILLA.zip", 
            "filepath": "/arrow-12.1/RMX2020/Arrow-v12.1-RMX2020-OFFICIAL-20220416-VANILLA.zip", 
            "maintainer": "sarthakroy2002", 
            "model": "realme Monet", 
            "oem": "realme", 
            "sha256": "fb76fe1af98c2a46e3941455ed90853d0053821f591e2ec92220c4ded821da58", 
            "size": "943623424", 
            "type": "official", 
            "version": "v12.1"
        }
    ], 
    "alioth": [
        {
            "changelog": "- overlays: Improve physical location of side fps\r\n- parts: Thermal settings app list improvement\r\n- Update blobs and tree to V13.0.2.0.SKHMIXM\r\n- Force set vendor.display.{idle_time,idle_time_inactive} to 0\r\n- Enable debug.sf.enable_hwc_vds\r\n- Misc fixes and upstream changes.\r\n\r\nKernel changelog:\r\n- input: misc: aw8697_haptic: Upgrade from zeus-s-oss\r\n- ARM64: dts: alioth: Use new awinic haptics configuration\r\n- Misc fixes and upstream changes.\r\n\r\n<b>- Installation instruction:</b> https://forum.xda-developers.com/t/rom-12-0-0-alioth-aliothin-arrowos-12-0-beta.4348617/post-85790097\r\n\r\n<b>- Recommend use with fw part MIUI V13.0.2.0.RKHMIXM (A12 Global) !!!</b>", 
            "date": "2022-04-19", 
            "datetime": "20220419", 
            "filename": "Arrow-v12.1-alioth-OFFICIAL-20220419-VANILLA.zip", 
            "filepath": "/arrow-12.1/alioth/Arrow-v12.1-alioth-OFFICIAL-20220419-VANILLA.zip", 
            "maintainer": "palaych", 
            "model": "Poco F3", 
            "oem": "POCO", 
            "sha256": "9271483da57408b925d58d8a1765e5106ed525eb2c6583b8eb7f82f91f4caec5", 
            "size": "1029301569", 
            "type": "official", 
            "version": "v12.1"
        }
    ], 
    "apollo": [
        {
            "changelog": "***Required Firmware and Recovery included with ROM***\r\n\r\nUse Arrow Recovery for installation & updates:\r\nXDA: https://forum.xda-developers.com/t/rom-un-official-12-beta-arrowos-vanilla-gapps-aosp.4353927/\r\nTelegram: https://t.me/arrowapolloofficial", 
            "date": "2022-04-16", 
            "datetime": "20220416", 
            "filename": "Arrow-v12.1-apollo-OFFICIAL-20220416-VANILLA.zip", 
            "filepath": "/arrow-12.1/apollo/Arrow-v12.1-apollo-OFFICIAL-20220416-VANILLA.zip", 
            "maintainer": "Dobsgw", 
            "model": "Xiaomi Mi 10T", 
            "oem": "Xiaomi", 
            "sha256": "1d68f39e45992edf643a0c143e7397efa87ab5690056cbded2fc671b430b0d39", 
            "size": "1349918282", 
            "type": "official", 
            "version": "v12.1"
        }
    ], 
    "avicii": [
        {
            "changelog": "Merged android-12.1.0_r4\r\nAdded TouchGestures.\r\nAdapted TouchGestures to Android 12 style\r\nUsed new rebased kernel\r\nThermal-engine from OOS", 
            "date": "2022-04-17", 
            "datetime": "20220417", 
            "filename": "Arrow-v12.1-avicii-OFFICIAL-20220417-VANILLA.zip", 
            "filepath": "/arrow-12.1/avicii/Arrow-v12.1-avicii-OFFICIAL-20220417-VANILLA.zip", 
            "maintainer": "Keertesh", 
            "model": "AC2001", 
            "oem": "OnePlus", 
            "sha256": "cd1fd080576d6fae8c264119cb650a26c88cf34ce7bd3a579b05b4800408f633", 
            "size": "1129642713", 
            "type": "official", 
            "version": "v12.1"
        }
    ], 
    "blueline": [
        {
            "changelog": null, 
            "date": "2022-04-16", 
            "datetime": "20220416", 
            "filename": "Arrow-v12.1-blueline-OFFICIAL-20220416-VANILLA.zip", 
            "filepath": "/arrow-12.1/blueline/Arrow-v12.1-blueline-OFFICIAL-20220416-VANILLA.zip", 
            "maintainer": "ReallySnow", 
            "model": "Pixel 3", 
            "oem": "google", 
            "sha256": "d0dcb13cb83da6e955c3f0e741154bcb38b89af643a698ed51aef027e3646780", 
            "size": "854592952", 
            "type": "official", 
            "version": "v12.1"
        }
    ], 
    "daisy": [
        {
            "changelog": null, 
            "date": "2022-04-17", 
            "datetime": "20220417", 
            "filename": "Arrow-v12.1-daisy-OFFICIAL-20220417-VANILLA.zip", 
            "filepath": "/arrow-12.1/daisy/Arrow-v12.1-daisy-OFFICIAL-20220417-VANILLA.zip", 
            "maintainer": "acras", 
            "model": "Mi A2 Lite", 
            "oem": "Xiaomi", 
            "sha256": "fd93dcce1ad00be97079bd7399429ead22f0654bb1fe66d16aa2dc6f06709ff0", 
            "size": "672510280", 
            "type": "official", 
            "version": "v12.1"
        }
    ], 
    "davinci": [
        {
            "changelog": "* Add back check for baseband version\r\n* Update common vendor to sweet MIUI 13 (Android 12)\r\n* Update some hals and gps\r\n* Update to latest Arian kernel\r\n* Remove powerhint modifications and go back to stock", 
            "date": "2022-04-19", 
            "datetime": "20220419", 
            "filename": "Arrow-v12.1-davinci-OFFICIAL-20220419-VANILLA.zip", 
            "filepath": "/arrow-12.1/davinci/Arrow-v12.1-davinci-OFFICIAL-20220419-VANILLA.zip", 
            "maintainer": "RemyL", 
            "model": "Mi 9T", 
            "oem": "Xiaomi", 
            "sha256": "ef4cb6ea2f978fcd8b460ecffd77f137c8ddf06ca83bd97bad42bb16a6b605a7", 
            "size": "983946856", 
            "type": "official", 
            "version": "v12.1"
        }
    ], 
    "lavender": [
        {
            "changelog": "- Flatten APEXs for performance\r\n- Added OpenGL ES and update Vulkan dEQP feature flags\r\n- Switched default camera app to GCamGo-V2\r\n- Now we use 4G icon instead of LTE in status bar\r\n- Improved thermal profile app listing\r\n- Enabled vibration effect in more environments\r\n- Uprev bluetooth audio HIDL impl to 2.1\r\n- Other fixes and improvements", 
            "date": "2022-04-19", 
            "datetime": "20220419", 
            "filename": "Arrow-v12.1-lavender-OFFICIAL-20220419-VANILLA.zip", 
            "filepath": "/arrow-12.1/lavender/Arrow-v12.1-lavender-OFFICIAL-20220419-VANILLA.zip", 
            "maintainer": "Ratoriku, Hazama25", 
            "model": "Redmi Note 7", 
            "oem": "Xiaomi", 
            "sha256": "c31cf5c6b6f50b8e26b2edd8f2a490b39324084a7ad303af7b376623941142b6", 
            "size": "863368432", 
            "type": "official", 
            "version": "v12.1"
        }
    ], 
    "lisa": [
        {
            "changelog": "- Initial Android 12.1 release.", 
            "date": "2022-03-23", 
            "datetime": "20220323", 
            "filename": "Arrow-v12.1-lisa-OFFICIAL-20220323-VANILLA.zip", 
            "filepath": "/arrow-12.1/lisa/Arrow-v12.1-lisa-OFFICIAL-20220323-VANILLA.zip", 
            "maintainer": "TG_DEVICE_MAINTAINER", 
            "model": "11 Lite 5G NE", 
            "oem": "Xiaomi", 
            "sha256": "a9699686ab0e7b6af1cb3d0c98a382f45506b1836646e1d833571f26f727103e", 
            "size": "1253554524", 
            "type": "official", 
            "version": "v12.1"
        }
    ], 
    "merlinx": [
        {
            "changelog": null, 
            "date": "2022-04-16", 
            "datetime": "20220416", 
            "filename": "Arrow-v12.1-merlinx-OFFICIAL-20220416-VANILLA.zip", 
            "filepath": "/arrow-12.1/merlinx/Arrow-v12.1-merlinx-OFFICIAL-20220416-VANILLA.zip", 
            "maintainer": "surblazer", 
            "model": "Redmi Note 9", 
            "oem": "Redmi", 
            "sha256": "94ed7a3866a75b7d9278d2043fbce5b94d8c18a8bc4bec3a3b1801124aa0869b", 
            "size": "871524182", 
            "type": "official", 
            "version": "v12.1"
        }
    ], 
    "miatoll": [
        {
            "changelog": "\u2022 Upstreamed kernel to 4.14.275\r\n\u2022 Merged tag \"LA.UM.9.1.r1-11800-SMxxx0.0\" in treewide, qcacld-3.0, fw-api, qca-wifi-host-cmn, techpack/audio\r\n\u2022 Switched to new AIDL power hal\r\n\u2022 Add custom boost extension for scroll handling\r\n\u2022 Add custom mode extension for handling app launch\r\n\u2022 Bump max interactive duration to 5s\r\n\u2022 Turn on GPU protected composition (Fixes black PiP window in Netflix or other apps)\r\n\u2022 Switched to new XiaomiDoze implementation\r\n\u2022 Adapt XiaomiDoze to S style\r\n\u2022 Adapt XiaomiParts to S style\r\n\u2022 Label camera fmq props\r\n\u2022 Disable proximity usage during doze\r\n\u2022 Switch to AOSP/Pixel offline charging animation\r\n\u2022 Switched back to QTI WFD\r\n\u2022 Enable debug.sf.enable_hwc_vds\r\n\u2022 Added missing lib needed for depth camera sensor\r\n\u2022 Updated default screen density to 420\r\n\u2022 Converted all overlays into RR0 overlays\r\n\u2022 Disabled s2idle\r\n\u2022 Aligned audio properties with CAF\r\n\u2022 Use appropriate message on flashing vbmeta\r\n\u2022 Enable iorapd tracing with perfetto\r\n\u2022 Fixed deprecated power profile items\r\n\u2022 Set readahead_size_kb=128 to system and data\r\n\u2022 Ignore CNE in location indicator\r\n\u2022 Thermal settings app list improvement\r\n\u2022 Include Arrow recovery (optional)\r\n\u2022 Adjust statusbar paddings\r\n\u2022 Address camera related denials\r\n\u2022 Label remaining wakeup nodes\r\n\u2022 Allow all filesystems for USB-OTG", 
            "date": "2022-04-19", 
            "datetime": "20220419", 
            "filename": "Arrow-v12.1-miatoll-OFFICIAL-20220419-VANILLA.zip", 
            "filepath": "/arrow-12.1/miatoll/Arrow-v12.1-miatoll-OFFICIAL-20220419-VANILLA.zip", 
            "maintainer": "SonalSingh18", 
            "model": "Miatoll", 
            "oem": "Xiaomi", 
            "sha256": "06cbb041bfeed1cfc60415e6598746505d5f010e32aadd0987e57ea199f63941", 
            "size": "1098788222", 
            "type": "official", 
            "version": "v12.1"
        }
    ], 
    "surya": [
        {
            "changelog": "- Update blobs to V12.5.5.0.RJGMIXM\r\n- Update IMS blobs from sweet A12\r\n- Misc fixes and upstream changes.\r\n\r\n<b>Note: Clean flash is MUST for arrow-12.0 (Android 12) !!!</b>", 
            "date": "2022-04-18", 
            "datetime": "20220418", 
            "filename": "Arrow-v12.1-surya-OFFICIAL-20220418-VANILLA.zip", 
            "filepath": "/arrow-12.1/surya/Arrow-v12.1-surya-OFFICIAL-20220418-VANILLA.zip", 
            "maintainer": "Ganesh Varma, palaych", 
            "model": "POCO X3 NFC", 
            "oem": "POCO", 
            "sha256": "1866f76ff2c5ab8de84c2dad26c2912d9505a1d665c8eba090d7dd7b4c50e446", 
            "size": "1004379352", 
            "type": "official", 
            "version": "v12.1"
        }
    ], 
    "sweet": [
        {
            "changelog": "28/02/2022\r\n\u2022 Updated blobs from MIUI 13 v13.0.2.0 Global\r\n\u2022 Fixed Ok Google\r\n\u2022 Updated GPS to LA.UM.9.1.r1-11500-SMxxx0.0\r\n\u2022 Fixed OTA updates\r\n\r\n12/11/2021\r\n\u2022 Improved power management\r\n\u2022 Switched back to schedutil governor\r\n\u2022 Cleaned unneeded vendor libraries\r\n\r\n28/10/2021\r\n\u2022 Fixed cutout color being inverted with the \"Force dark theme\" setting\r\n\u2022 Fixed minimum frequency being 1248MHz\r\n\u2022 Fixed WFD\r\n\u2022 Added Spanish translations to the device specific settings", 
            "date": "2022-04-16", 
            "datetime": "20220416", 
            "filename": "Arrow-v12.1-sweet-OFFICIAL-20220416-VANILLA.zip", 
            "filepath": "/arrow-12.1/sweet/Arrow-v12.1-sweet-OFFICIAL-20220416-VANILLA.zip", 
            "maintainer": "daniml3", 
            "model": "Redmi Note 10 Pro", 
            "oem": "Redmi", 
            "sha256": "b9be67abca3f7af61721f982f0229eeacfea7d7df021b40285f871fbc62cb09d", 
            "size": "1069736315", 
            "type": "official", 
            "version": "v12.1"
        }
    ], 
    "taimen": [
        {
            "changelog": "- Flatten APEXs for performance\r\n- Re-enable Now Playing", 
            "date": "2022-04-16", 
            "datetime": "20220416", 
            "filename": "Arrow-v12.1-taimen-OFFICIAL-20220416-VANILLA.zip", 
            "filepath": "/arrow-12.1/taimen/Arrow-v12.1-taimen-OFFICIAL-20220416-VANILLA.zip", 
            "maintainer": "ReallySnow", 
            "model": "Pixel 2 XL", 
            "oem": "google", 
            "sha256": "22c7723d6468ed8a817c8e7aa996e0a74af28a9d381d47e950c4c80810dd3bce", 
            "size": "782880498", 
            "type": "official", 
            "version": "v12.1"
        }
    ], 
    "vayu": [
        {
            "changelog": null, 
            "date": "2022-04-18", 
            "datetime": "20220418", 
            "filename": "Arrow-v12.1-vayu-OFFICIAL-20220418-VANILLA.zip", 
            "filepath": "/arrow-12.1/vayu/Arrow-v12.1-vayu-OFFICIAL-20220418-VANILLA.zip", 
            "maintainer": "kubersharma001", 
            "model": "Poco X3 Pro", 
            "oem": "POCO", 
            "sha256": "a23262e573c59c497c0021551575f909e2f315d33456fe0bd86d0d593f4ba70d", 
            "size": "1146800045", 
            "type": "official", 
            "version": "v12.1"
        }
    ], 
    "whyred": [
        {
            "changelog": "\u2022 Clean up some blobs\r\n\u2022 Add local FileUtils\r\n\u2022 Refactor the whole code and adapt parts to S style\r\n\u2022 Add bass booster preset for MiSound\r\n\u2022 Do not sign Wifi RROs with platform cert\r\n\u2022 Some misc changes and clean up", 
            "date": "2022-04-16", 
            "datetime": "20220416", 
            "filename": "Arrow-v12.1-whyred-OFFICIAL-20220416-VANILLA.zip", 
            "filepath": "/arrow-12.1/whyred/Arrow-v12.1-whyred-OFFICIAL-20220416-VANILLA.zip", 
            "maintainer": "Sreekanth", 
            "model": "Redmi Note 5", 
            "oem": "Xiaomi", 
            "sha256": "168ea5d7bc664adc0ecf387ffcc3c50c08ecfc0fffbd25864be663bdd844aacf", 
            "size": "769712772", 
            "type": "official", 
            "version": "v12.1"
        }
    ]
}